<?xml version="1.0" encoding="UTF-8"?>
<objects serializationModel="Studio.02.02.00">
	<object class="AudioFile" id="{19324669-b339-4b50-a779-ff9d3e449161}">
		<property name="assetPath">
			<value>SFX/Plate/FreeSound - Dinnerplate - rabban625 - Trimmed (07).wav</value>
		</property>
		<property name="frequencyInKHz">
			<value>44.0999985</value>
		</property>
		<property name="channelCount">
			<value>1</value>
		</property>
		<property name="length">
			<value>0.39997732426303856</value>
		</property>
		<relationship name="masterAssetFolder">
			<destination>{e3383467-48de-4231-963e-4d2c3df9dcf5}</destination>
		</relationship>
	</object>
</objects>
