<?xml version="1.0" encoding="UTF-8"?>
<objects serializationModel="Studio.02.02.00">
	<object class="AudioFile" id="{ffd41fd8-7045-4b4a-8e3b-ffb7fdea2de1}">
		<property name="assetPath">
			<value>SFX/Hammer/FreeSound - Hammer Against Stone - Robinhood76.wav</value>
		</property>
		<property name="frequencyInKHz">
			<value>44.0999985</value>
		</property>
		<property name="channelCount">
			<value>2</value>
		</property>
		<property name="length">
			<value>1.1182993197278912</value>
		</property>
		<relationship name="masterAssetFolder">
			<destination>{e3383467-48de-4231-963e-4d2c3df9dcf5}</destination>
		</relationship>
	</object>
</objects>
